{
  "navbar": [
    { "label": "Home", "link": "/" },
    { "label": "Shop", "link": "/shop" },
    { "label": "About us", "link": "/about" },
    { "label": "Services", "link": "/services" },
    { "label": "Blog", "link": "/blog" },
    { "label": "Cart", "link": "/cart" }
  ],
  "header": {
    "title": "Modern Interior ",
    "titleone": "Design Studio",
    "subtitle": "Donec vitae odio quis nisl dapibus malesuada. Nullam ac aliquet velit. Aliquam vulputate velit imperdiet dolor tempor tristique.",
    "buttons": [
      { "label": "Shop Now", "id": "shop" }
    ],
    "buttons1": [
      { "label": "Explore", "id": "explore" }
    ],
    "image": "./Images/couch.png",
    "imageAlt": "Sofa"
  },
  "products": [
    {
      "id": 1,
      "title": "Nordic Dime Chair",
      "price": "$50.00",
      "image": "./Images/product-1.png"
    },
    {
      "id": 2,
      "title": "Kruzo Aero Chair",
      "price": "$78.00",
      "image": "./Images/product-2.png"
    },
    {
      "id": 3,
      "title": "Ergonomic Chair",
      "price": "$43.00",
      "image": "./Images/product-3.png"
    }
  ],
  "whyChooseUs": {
    "sectionTitle": "Why Choose Us",
    "sectionDescription": "Donec vitae odio quis nisl dapibus malesuada. Nullam ac aliquet velit. Aliquam vulputate velit imperdiet dolor tempor tristique.",
    "features": [
      {
        "icon": "FaShippingFast",
        "title": "Fast & Free Shipping",
        "description": "Donec vitae odio quis nisl dapibus malesuada. Nullam ac aliquet velit. Aliquam vulputate."
      },
      {
        "icon": "FaShoppingBag",
        "title": "Easy to Shop",
        "description": "Donec vitae odio quis nisl dapibus malesuada. Nullam ac aliquet velit. Aliquam vulputate."
      },
      {
        "icon": "FaHeadset",
        "title": "24/7 Support",
        "description": "Donec vitae odio quis nisl dapibus malesuada. Nullam ac aliquet velit. Aliquam vulputate."
      },
      {
        "icon": "FaExchangeAlt",
        "title": "Hassle Free Returns",
        "description": "Donec vitae odio quis nisl dapibus malesuada. Nullam ac aliquet velit. Aliquam vulputate."
      }
    ],
    "images": {
      "mainImage": "./Images/why-choose-us-img.jpg",
      "dotsImage": "./Images/dots-yellow.svg"
    }
  },
  "sectionFour": {
    "heading": "We Help You Make Modern Interior Design",
    "description": "Donec facilisis quam ut purus rutrum lobortis. Donec vitae odio quis nisl dapibus malesuada. Nulla ac aliquet velit. Aliquam vulputate velit imperdiet dolor tempor tristique.",
    "images": {
      "dots": "./Images/dots-green.svg",
      "product": "./Images/product.png"
    },
    "features": [
      {
        "icon": "FaRegCircle",
        "text": "Donec vitae odio quis nisl dapibus malesuada Lorem, ipsum."
      },
      {
        "icon": "FaRegCircle",
        "text": "Donec vitae odio quis nisl Lorem, ipsum dolor. dapibus malesuada."
      },
      {
        "icon": "FaRegCircle",
        "text": "Donec Lorem ipsum dolor sit amet. vitae odio quis nisl."
      },
      {
        "icon": "FaRegCircle",
        "text": "Donec vitae Lorem ipsum dolor sit amet. odio quis nisl malesuada."
      }
    ], 
    "buttonsfour": [
      { "label": "Explore", "id": "explore" }
    ]
  },
  "sectionfive": [
    {
      "id": 1,
      "name": "Nordic Chair",
      "description": "Donec facilisis quam ut purus rutrum lobortis. Donec vitae odio",
      "image": "./Images/product-1.png"
    },
    {
      "id": 2,
      "name": "Kruzo Aero Chair",
      "description": "Donec facilisis quam ut purus rutrum lobortis. Donec vitae odio",
      "image": "./Images/product-2.png"
    },
    {
      "id": 3,
      "name": "Ergonomic Chair",
      "description": "Donec facilisis quam ut purus rutrum lobortis. Donec vitae odio",
      "image": "./Images/product-3.png"
    }
  ],
  "testimonials":[
    {
      "id": 1,
      "content": "“Donec facilisis quam ut purus rutrum lobortis. Donec vitae odio quis nisl dapibus malesuada. Nullam ac aliquet velit. Aliquam vulputate velit imperdiet dolor tempor tristique. Pellentesque habitant morbi tristique senectus et netus et malesuada fames ac turpis egestas. Integer convallis volutpat dui quis scelerisque.”",
      "img": "./Images/person-1.png",
      "name": "Maria Jones",
      "designation": "CEO, Co-Founder, XYZ Inc."
    },
    {
      "id": 2,
      "content": "“Donec facilisis quam ut purus rutrum lobortis. Donec vitae odio quis nisl dapibus malesuada. Nullam ac aliquet velit. Aliquam vulputate velit imperdiet dolor tempor tristique. Pellentesque habitant morbi tristique senectus et netus et malesuada fames ac turpis egestas. Integer convallis volutpat dui quis scelerisque.”",
      "img": "./Images/person_2.jpg",
      "name": "John Doe",
      "designation": "CTO, ABC Corp."
    },
    {
      "id": 3,
      "content": "“Donec facilisis quam ut purus rutrum lobortis. Donec vitae odio quis nisl dapibus malesuada. Nullam ac aliquet velit. Aliquam vulputate velit imperdiet dolor tempor tristique. Pellentesque habitant morbi tristique senectus et netus et malesuada fames ac turpis egestas. Integer convallis volutpat dui quis scelerisque.”",
      "img": "./Images/person_3.jpg",
      "name": "Jimmy",
      "designation": "CTS, TCS Corp."
    }
  ],
  "blogPosts":[
    {
      "id": 1,
      "title": "First Time Home Owner Ideas",
      "author": "Kristin Watson",
      "date": "Dec 19, 2024",
      "imageUrl": "./Images/post-1.jpg"
    },
    {
      "id":2,
      "title": "How To Keep Your Furniture Clean",
      "author": "Robert Fox",
      "date": "Nov 15, 2024",
      "imageUrl": "./Images/post-2.jpg"
    },
    {
      "id":3,
      "title": "Small Space Furniture Apartment Ideas",
      "author": "Kristin Watson",
      "date": "Feb 12, 2024",
      "imageUrl": "./Images/post-3.jpg"
    }
  ],
  "Footer":{
    "brandName": "Furni.",
    "newsletterTitle": "Subscribe to Newsletter",
    "footerDescription": "Donec facilisis quam ut purus rutrum lobortis. Donec vitae odio quis nisl dapibus malesuada.",
    "socialLinks": [
      { "icon": "FaFacebookF", "url": "https://facebook.com" },
      { "icon": "FaTwitter", "url": "https://twitter.com" },
      { "icon": "FaInstagram", "url": "https://instagram.com" },
      { "icon": "FaLinkedinIn", "url": "https://linkedin.com" }
    ],
    "footerLinks": [
      {
        "title": "Company",
        "links": ["About us", "Services", "Blog", "Contact us"]
      },
      {
        "title": "Support",
        "links": ["Support", "Knowledge base", "Live chat"]
      },
      {
        "title": "Company Info",
        "links": ["Jobs", "Our team", "Leadership", "Privacy Policy"]
      },
      {
        "title": "Products",
        "links": ["Nordic Chair", "Kruzo Aero", "Ergonomic Chair"]
      }
    ],
    "copyright": "©2024. All Rights Reserved.- Designed By Anandh",
    "Terms":"Terms & Conditions",
    "privacy":"Privacy Policy"
  },
  "shop":[
    {
      "id": 1,
      "title": "Nordic Chair",
      "price": "$50.00",
      "image": "./Images/product-1.png"
    },
    {
      "id": 2,
      "title": "Kruzo Aero Chair",
      "price": "$78.00",
      "image": "./Images/product-2.png"
    },
    {
      "id": 3,
      "title": "Ergonomic Chair",
      "price": "$43.00",
      "image": "./Images/product-3.png"
    },
    {
      "id": 4,
      "title": "Nordic Chair",
      "price": "$50.00",
      "image": "./Images/product-1.png"
    },
    {
      "id": 5,
      "title": "Ergonomic Chair",
      "price": "$43.00",
      "image": "./Images/product-2.png"
    },
    {
      "id": 6,
      "title": "Nordic Chair",
      "price": "$50.00",
      "image": "./Images/product-1.png"
    },
    {
      "id": 7,
      "title": "Ergonomic Chair",
      "price": "$43.00",
      "image": "./Images/product-3.png"
    },
    {
      "id": 8,
      "title": "Kruzo Deluxe Chair",
      "price": "$99.00",
      "image": "./Images/product-2.png"
    }
  ]

}
